sb_portal_gun/__init__.py
sb_portal_gun/__main__.py
sb_portal_gun/main.py
sb_portal_gun-0.1.0.dist-info/entry_points.txt
sb_portal_gun-0.1.0.dist-info/WHEEL
sb_portal_gun-0.1.0.dist-info/METADATA
sb_portal_gun-0.1.0.dist-info/RECORD
